[
  {
    "asin": "B07JBXM83R",
    "image": [
      50,
      49,
      57,
      111,
      72,
      84,
      75,
      114,
      85,
      57,
      76,
      46,
      106,
      112,
      103
    ],
    "newprice": 20539,
    "pricedifference": 7670,
    "dealscore": 148245,
    "rootcat": "172282",
    "savingspercent": 3734,
    "title": "NETGEAR Orbi Home Mesh WiFi System (RBK50) (Renewed)",
    "usedprice": 12871,
    "updated_at": "2024-09-12T05:50:07.360Z",
    "lastchange": "2024-09-11T07:03:31.111Z",
    "lastupdate": 7204260,
    "source": 5
  }
]
